[{"Rise Up Australia": "14", "Drug Law Reform": "4", "Palmer United Australia": "18", "Australian Sex Party": "2", "Voluntary Euthanasia": "6", "Bullet Train For Australia": "8", "The Greens": "21", "Australian Independents": "0", "Katter's Australian Party": "16", "Coalition (Lib/Nat)": "23", "Australian Labor Party": "25", "Animal Justice Party": "10", "Party": "Australian Independents", "Stable Population Party": "12"}, {"Rise Up Australia": "14", "Drug Law Reform": "12", "Palmer United Australia": "16", "Australian Sex Party": "10", "Voluntary Euthanasia": "8", "Bullet Train For Australia": "4", "The Greens": "25", "Australian Independents": "6", "Katter's Australian Party": "22", "Coalition (Lib/Nat)": "20", "Australian Labor Party": "18", "Animal Justice Party": "0", "Party": "Animal Justice Party", "Stable Population Party": "2"}, {"Rise Up Australia": "23", "Drug Law Reform": "12", "Palmer United Australia": "16", "Australian Sex Party": "8", "Voluntary Euthanasia": "14", "Bullet Train For Australia": "4", "The Greens": "2", "Australian Independents": "21", "Katter's Australian Party": "6", "Coalition (Lib/Nat)": "25", "Australian Labor Party": "0", "Animal Justice Party": "10", "Party": "Australian Labor Party", "Stable Population Party": "18"}, {"Rise Up Australia": "25", "Drug Law Reform": "4", "Palmer United Australia": "20", "Australian Sex Party": "0", "Voluntary Euthanasia": "2", "Bullet Train For Australia": "8", "The Greens": "14", "Australian Independents": "12", "Katter's Australian Party": "18", "Coalition (Lib/Nat)": "22", "Australian Labor Party": "16", "Animal Justice Party": "6", "Party": "Australian Sex Party", "Stable Population Party": "10"}, {"Rise Up Australia": "25", "Drug Law Reform": "11", "Palmer United Australia": "19", "Australian Sex Party": "13", "Voluntary Euthanasia": "9", "Bullet Train For Australia": "0", "The Greens": "15", "Australian Independents": "3", "Katter's Australian Party": "17", "Coalition (Lib/Nat)": "23", "Australian Labor Party": "21", "Animal Justice Party": "7", "Party": "Bullet Train For Australia", "Stable Population Party": "5"}, {"Rise Up Australia": "9", "Drug Law Reform": "15", "Palmer United Australia": "7", "Australian Sex Party": "17", "Voluntary Euthanasia": "20", "Bullet Train For Australia": "2", "The Greens": "25", "Australian Independents": "13", "Katter's Australian Party": "6", "Coalition (Lib/Nat)": "0", "Australian Labor Party": "23", "Animal Justice Party": "5", "Party": "Coalition (Lib/Nat)", "Stable Population Party": "4"}, {"Rise Up Australia": "17", "Drug Law Reform": "0", "Palmer United Australia": "15", "Australian Sex Party": "2", "Voluntary Euthanasia": "13", "Bullet Train For Australia": "23", "The Greens": "4", "Australian Independents": "10", "Katter's Australian Party": "25", "Coalition (Lib/Nat)": "8", "Australian Labor Party": "6", "Animal Justice Party": "19", "Party": "Drug Law Reform", "Stable Population Party": "21"}, {"Rise Up Australia": "25", "Drug Law Reform": "4", "Palmer United Australia": "17", "Australian Sex Party": "8", "Voluntary Euthanasia": "6", "Bullet Train For Australia": "2", "The Greens": "0", "Australian Independents": "10", "Katter's Australian Party": "12", "Coalition (Lib/Nat)": "23", "Australian Labor Party": "14", "Animal Justice Party": "21", "Party": "The Greens", "Stable Population Party": "19"}, {"Rise Up Australia": "8", "Drug Law Reform": "14", "Palmer United Australia": "4", "Australian Sex Party": "22", "Voluntary Euthanasia": "25", "Bullet Train For Australia": "2", "The Greens": "16", "Australian Independents": "6", "Katter's Australian Party": "0", "Coalition (Lib/Nat)": "18", "Australian Labor Party": "20", "Animal Justice Party": "10", "Party": "Katter's Australian Party", "Stable Population Party": "12"}, {"Rise Up Australia": "5", "Drug Law Reform": "25", "Palmer United Australia": "0", "Australian Sex Party": "9", "Voluntary Euthanasia": "15", "Bullet Train For Australia": "7", "The Greens": "17", "Australian Independents": "2", "Katter's Australian Party": "13", "Coalition (Lib/Nat)": "21", "Australian Labor Party": "23", "Animal Justice Party": "11", "Party": "Palmer United Australia", "Stable Population Party": "19"}, {"Rise Up Australia": "0", "Drug Law Reform": "18", "Palmer United Australia": "8", "Australian Sex Party": "22", "Voluntary Euthanasia": "20", "Bullet Train For Australia": "2", "The Greens": "24", "Australian Independents": "4", "Katter's Australian Party": "12", "Coalition (Lib/Nat)": "6", "Australian Labor Party": "16", "Animal Justice Party": "14", "Party": "Rise Up Australia", "Stable Population Party": "10"}, {"Rise Up Australia": "25", "Drug Law Reform": "8", "Palmer United Australia": "23", "Australian Sex Party": "12", "Voluntary Euthanasia": "10", "Bullet Train For Australia": "4", "The Greens": "17", "Australian Independents": "2", "Katter's Australian Party": "14", "Coalition (Lib/Nat)": "21", "Australian Labor Party": "19", "Animal Justice Party": "6", "Party": "Stable Population Party", "Stable Population Party": "0"}, {"Rise Up Australia": "22", "Drug Law Reform": "8", "Palmer United Australia": "14", "Australian Sex Party": "2", "Voluntary Euthanasia": "0", "Bullet Train For Australia": "12", "The Greens": "16", "Australian Independents": "4", "Katter's Australian Party": "20", "Coalition (Lib/Nat)": "24", "Australian Labor Party": "18", "Animal Justice Party": "10", "Party": "Voluntary Euthanasia", "Stable Population Party": "6"}]